{
 "creation": "2019-12-24 09:27:05.757574",
 "doctype": "DocType",
 "editable_grid": 1,
 "engine": "InnoDB",
 "field_order": [
  "sales_invoice",
  "customer",
  "customer_name"
 ],
 "fields": [
  {
   "fieldname": "sales_invoice",
   "fieldtype": "Link",
   "in_list_view": 1,
   "label": "Sales Invoice",
   "options": "Sales Invoice",
   "reqd": 1
  },
  {
   "fetch_from": "sales_invoice.customer",
   "fieldname": "customer",
   "fieldtype": "Data",
   "in_list_view": 1,
   "label": "Customer",
   "read_only": 1
  },
  {
   "fetch_from": "sales_invoice.customer_name",
   "fieldname": "customer_name",
   "fieldtype": "Data",
   "label": "Customer Name",
   "read_only": 1
  }
 ],
 "istable": 1,
 "modified": "2019-12-24 09:27:05.757574",
 "modified_by": "Administrator",
 "module": "Spinadent",
 "name": "Sammelrechnung Rechnung",
 "owner": "Administrator",
 "permissions": [],
 "quick_entry": 1,
 "sort_field": "modified",
 "sort_order": "DESC",
 "track_changes": 1
}